[
  {
    "date": "2025-11-02",
    "close": 23046.0,
    "open": 23157.0,
    "high": 23507.0,
    "low": 22585.0,
    "volume": 209938000
  },
  {
    "date": "2025-11-03",
    "close": 22617.0,
    "open": 22594.0,
    "high": 23069.0,
    "low": 22165.0,
    "volume": 3255779000
  },
  {
    "date": "2025-11-04",
    "close": 22951.0,
    "open": 23046.0,
    "high": 23410.0,
    "low": 22492.0,
    "volume": 2371107000
  },
  {
    "date": "2025-11-05",
    "close": 22537.0,
    "open": 22432.0,
    "high": 22988.0,
    "low": 22086.0,
    "volume": 2108472000
  },
  {
    "date": "2025-11-06",
    "close": 22803.0,
    "open": 22676.0,
    "high": 23259.0,
    "low": 22347.0,
    "volume": 1565530000
  },
  {
    "date": "2025-11-07",
    "close": 22873.0,
    "open": 22824.0,
    "high": 23330.0,
    "low": 22415.0,
    "volume": 3726391000
  },
  {
    "date": "2025-11-08",
    "close": 22719.0,
    "open": 22834.0,
    "high": 23173.0,
    "low": 22265.0,
    "volume": 1417357000
  },
  {
    "date": "2025-11-09",
    "close": 22536.0,
    "open": 22489.0,
    "high": 22987.0,
    "low": 22086.0,
    "volume": 1627517000
  },
  {
    "date": "2025-11-10",
    "close": 22737.0,
    "open": 22580.0,
    "high": 23192.0,
    "low": 22283.0,
    "volume": 4255645000
  },
  {
    "date": "2025-11-11",
    "close": 22769.0,
    "open": 22823.0,
    "high": 23224.0,
    "low": 22313.0,
    "volume": 754947000
  },
  {
    "date": "2025-11-12",
    "close": 23051.0,
    "open": 22869.0,
    "high": 23512.0,
    "low": 22590.0,
    "volume": 4677296000
  },
  {
    "date": "2025-11-13",
    "close": 22551.0,
    "open": 22442.0,
    "high": 23002.0,
    "low": 22100.0,
    "volume": 2204247000
  },
  {
    "date": "2025-11-14",
    "close": 22998.0,
    "open": 22877.0,
    "high": 23458.0,
    "low": 22538.0,
    "volume": 4791664000
  },
  {
    "date": "2025-11-15",
    "close": 22353.0,
    "open": 22373.0,
    "high": 22800.0,
    "low": 21906.0,
    "volume": 988134000
  },
  {
    "date": "2025-11-16",
    "close": 22870.0,
    "open": 22867.0,
    "high": 23327.0,
    "low": 22413.0,
    "volume": 2367867000
  },
  {
    "date": "2025-11-17",
    "close": 22616.0,
    "open": 22647.0,
    "high": 23069.0,
    "low": 22164.0,
    "volume": 1017983000
  },
  {
    "date": "2025-11-18",
    "close": 22590.0,
    "open": 22702.0,
    "high": 23042.0,
    "low": 22139.0,
    "volume": 4805302000
  },
  {
    "date": "2025-11-19",
    "close": 22271.0,
    "open": 22125.0,
    "high": 22716.0,
    "low": 21825.0,
    "volume": 2807181000
  },
  {
    "date": "2025-11-20",
    "close": 23032.0,
    "open": 23070.0,
    "high": 23493.0,
    "low": 22572.0,
    "volume": 283810000
  },
  {
    "date": "2025-11-21",
    "close": 22827.0,
    "open": 22928.0,
    "high": 23283.0,
    "low": 22370.0,
    "volume": 461162000
  },
  {
    "date": "2025-11-22",
    "close": 22294.0,
    "open": 22479.0,
    "high": 22740.0,
    "low": 21848.0,
    "volume": 1862629000
  },
  {
    "date": "2025-11-23",
    "close": 23092.0,
    "open": 23202.0,
    "high": 23554.0,
    "low": 22630.0,
    "volume": 919826000
  },
  {
    "date": "2025-11-24",
    "close": 22796.0,
    "open": 22861.0,
    "high": 23252.0,
    "low": 22340.0,
    "volume": 4965232000
  },
  {
    "date": "2025-11-25",
    "close": 22377.0,
    "open": 22500.0,
    "high": 22825.0,
    "low": 21930.0,
    "volume": 3404663000
  },
  {
    "date": "2025-11-26",
    "close": 23045.0,
    "open": 22961.0,
    "high": 23506.0,
    "low": 22585.0,
    "volume": 1324285000
  },
  {
    "date": "2025-11-27",
    "close": 22983.0,
    "open": 22939.0,
    "high": 23442.0,
    "low": 22523.0,
    "volume": 4973433000
  },
  {
    "date": "2025-11-28",
    "close": 22505.0,
    "open": 22700.0,
    "high": 22955.0,
    "low": 22054.0,
    "volume": 2544748000
  },
  {
    "date": "2025-11-29",
    "close": 22454.0,
    "open": 22666.0,
    "high": 22903.0,
    "low": 22005.0,
    "volume": 1323795000
  },
  {
    "date": "2025-11-30",
    "close": 23092.0,
    "open": 22956.0,
    "high": 23554.0,
    "low": 22630.0,
    "volume": 2168070000
  },
  {
    "date": "2025-12-01",
    "close": 22639.0,
    "open": 22698.0,
    "high": 23091.0,
    "low": 22186.0,
    "volume": 4983225000
  },
  {
    "date": "2025-12-02",
    "close": 22947.0,
    "open": 23148.0,
    "high": 23406.0,
    "low": 22488.0,
    "volume": 2501698000
  },
  {
    "date": "2025-12-03",
    "close": 22879.0,
    "open": 23033.0,
    "high": 23337.0,
    "low": 22422.0,
    "volume": 3061265000
  },
  {
    "date": "2025-12-04",
    "close": 22620.0,
    "open": 22601.0,
    "high": 23073.0,
    "low": 22168.0,
    "volume": 993228000
  },
  {
    "date": "2025-12-05",
    "close": 22777.0,
    "open": 22645.0,
    "high": 23233.0,
    "low": 22321.0,
    "volume": 3369229000
  },
  {
    "date": "2025-12-06",
    "close": 22804.0,
    "open": 22840.0,
    "high": 23260.0,
    "low": 22348.0,
    "volume": 3342095000
  },
  {
    "date": "2025-12-07",
    "close": 23055.0,
    "open": 23022.0,
    "high": 23516.0,
    "low": 22594.0,
    "volume": 3890922000
  },
  {
    "date": "2025-12-08",
    "close": 22627.0,
    "open": 22450.0,
    "high": 23079.0,
    "low": 22174.0,
    "volume": 377983000
  },
  {
    "date": "2025-12-09",
    "close": 22474.0,
    "open": 22580.0,
    "high": 22924.0,
    "low": 22025.0,
    "volume": 240640000
  },
  {
    "date": "2025-12-10",
    "close": 22394.0,
    "open": 22335.0,
    "high": 22842.0,
    "low": 21946.0,
    "volume": 3247247000
  },
  {
    "date": "2025-12-11",
    "close": 23084.0,
    "open": 23034.0,
    "high": 23545.0,
    "low": 22622.0,
    "volume": 4395897000
  },
  {
    "date": "2025-12-12",
    "close": 22990.0,
    "open": 22883.0,
    "high": 23449.0,
    "low": 22530.0,
    "volume": 2471492000
  },
  {
    "date": "2025-12-13",
    "close": 22288.0,
    "open": 22089.0,
    "high": 22733.0,
    "low": 21842.0,
    "volume": 3219633000
  },
  {
    "date": "2025-12-14",
    "close": 22618.0,
    "open": 22736.0,
    "high": 23070.0,
    "low": 22166.0,
    "volume": 3479399000
  },
  {
    "date": "2025-12-15",
    "close": 22566.0,
    "open": 22595.0,
    "high": 23017.0,
    "low": 22115.0,
    "volume": 4982590000
  },
  {
    "date": "2025-12-16",
    "close": 22625.0,
    "open": 22593.0,
    "high": 23077.0,
    "low": 22172.0,
    "volume": 4115923000
  },
  {
    "date": "2025-12-17",
    "close": 22388.0,
    "open": 22236.0,
    "high": 22836.0,
    "low": 21940.0,
    "volume": 4666746000
  },
  {
    "date": "2025-12-18",
    "close": 22852.0,
    "open": 22821.0,
    "high": 23309.0,
    "low": 22395.0,
    "volume": 1682796000
  },
  {
    "date": "2025-12-19",
    "close": 22536.0,
    "open": 22638.0,
    "high": 22987.0,
    "low": 22086.0,
    "volume": 325050000
  },
  {
    "date": "2025-12-20",
    "close": 22952.0,
    "open": 22896.0,
    "high": 23411.0,
    "low": 22493.0,
    "volume": 4110742000
  },
  {
    "date": "2025-12-21",
    "close": 22822.0,
    "open": 23016.0,
    "high": 23279.0,
    "low": 22366.0,
    "volume": 2963560000
  },
  {
    "date": "2025-12-22",
    "close": 22587.0,
    "open": 22711.0,
    "high": 23039.0,
    "low": 22135.0,
    "volume": 1477474000
  },
  {
    "date": "2025-12-23",
    "close": 22709.0,
    "open": 22610.0,
    "high": 23163.0,
    "low": 22255.0,
    "volume": 957057000
  },
  {
    "date": "2025-12-24",
    "close": 22298.0,
    "open": 22128.0,
    "high": 22744.0,
    "low": 21852.0,
    "volume": 332432000
  },
  {
    "date": "2025-12-25",
    "close": 22513.0,
    "open": 22384.0,
    "high": 22964.0,
    "low": 22063.0,
    "volume": 4881430000
  },
  {
    "date": "2025-12-26",
    "close": 23102.0,
    "open": 23115.0,
    "high": 23564.0,
    "low": 22640.0,
    "volume": 3808948000
  },
  {
    "date": "2025-12-27",
    "close": 22600.0,
    "open": 22436.0,
    "high": 23052.0,
    "low": 22148.0,
    "volume": 1525542000
  },
  {
    "date": "2025-12-28",
    "close": 22937.0,
    "open": 23050.0,
    "high": 23396.0,
    "low": 22479.0,
    "volume": 3698586000
  },
  {
    "date": "2025-12-29",
    "close": 22386.0,
    "open": 22554.0,
    "high": 22833.0,
    "low": 21938.0,
    "volume": 1104584000
  },
  {
    "date": "2025-12-30",
    "close": 22457.0,
    "open": 22659.0,
    "high": 22907.0,
    "low": 22008.0,
    "volume": 2533785000
  },
  {
    "date": "2025-12-31",
    "close": 22796.0,
    "open": 22866.0,
    "high": 23252.0,
    "low": 22340.0,
    "volume": 2910194000
  },
  {
    "date": "2026-01-01",
    "close": 22333.0,
    "open": 22363.0,
    "high": 22780.0,
    "low": 21887.0,
    "volume": 4018279000
  },
  {
    "date": "2026-01-02",
    "close": 22815.0,
    "open": 22645.0,
    "high": 23271.0,
    "low": 22359.0,
    "volume": 1295789000
  },
  {
    "date": "2026-01-03",
    "close": 22424.0,
    "open": 22245.0,
    "high": 22873.0,
    "low": 21976.0,
    "volume": 4119045000
  },
  {
    "date": "2026-01-04",
    "close": 22567.0,
    "open": 22531.0,
    "high": 23018.0,
    "low": 22116.0,
    "volume": 2392178000
  },
  {
    "date": "2026-01-05",
    "close": 22672.0,
    "open": 22840.0,
    "high": 23125.0,
    "low": 22218.0,
    "volume": 3059233000
  },
  {
    "date": "2026-01-06",
    "close": 22951.0,
    "open": 23170.0,
    "high": 23410.0,
    "low": 22492.0,
    "volume": 332027000
  },
  {
    "date": "2026-01-07",
    "close": 22558.0,
    "open": 22485.0,
    "high": 23009.0,
    "low": 22107.0,
    "volume": 1698034000
  },
  {
    "date": "2026-01-08",
    "close": 22427.0,
    "open": 22505.0,
    "high": 22876.0,
    "low": 21979.0,
    "volume": 354048000
  },
  {
    "date": "2026-01-09",
    "close": 22771.0,
    "open": 22697.0,
    "high": 23227.0,
    "low": 22316.0,
    "volume": 3144229000
  },
  {
    "date": "2026-01-10",
    "close": 22808.0,
    "open": 22785.0,
    "high": 23264.0,
    "low": 22352.0,
    "volume": 1866123000
  },
  {
    "date": "2026-01-11",
    "close": 22822.0,
    "open": 22722.0,
    "high": 23279.0,
    "low": 22366.0,
    "volume": 3336541000
  },
  {
    "date": "2026-01-12",
    "close": 22412.0,
    "open": 22313.0,
    "high": 22860.0,
    "low": 21964.0,
    "volume": 1823096000
  },
  {
    "date": "2026-01-13",
    "close": 22752.0,
    "open": 22758.0,
    "high": 23207.0,
    "low": 22296.0,
    "volume": 646686000
  },
  {
    "date": "2026-01-14",
    "close": 22667.0,
    "open": 22802.0,
    "high": 23120.0,
    "low": 22213.0,
    "volume": 1674895000
  },
  {
    "date": "2026-01-15",
    "close": 22735.0,
    "open": 22651.0,
    "high": 23190.0,
    "low": 22281.0,
    "volume": 3088893000
  },
  {
    "date": "2026-01-16",
    "close": 22534.0,
    "open": 22702.0,
    "high": 22985.0,
    "low": 22083.0,
    "volume": 904985000
  },
  {
    "date": "2026-01-17",
    "close": 22608.0,
    "open": 22459.0,
    "high": 23060.0,
    "low": 22156.0,
    "volume": 543194000
  },
  {
    "date": "2026-01-18",
    "close": 22823.0,
    "open": 22826.0,
    "high": 23279.0,
    "low": 22367.0,
    "volume": 1090401000
  },
  {
    "date": "2026-01-19",
    "close": 22671.0,
    "open": 22620.0,
    "high": 23124.0,
    "low": 22217.0,
    "volume": 627142000
  },
  {
    "date": "2026-01-20",
    "close": 22356.0,
    "open": 22262.0,
    "high": 22804.0,
    "low": 21909.0,
    "volume": 2861435000
  },
  {
    "date": "2026-01-21",
    "close": 22329.0,
    "open": 22295.0,
    "high": 22776.0,
    "low": 21883.0,
    "volume": 893771000
  },
  {
    "date": "2026-01-22",
    "close": 22400.0,
    "open": 22613.0,
    "high": 22848.0,
    "low": 21952.0,
    "volume": 1111786000
  },
  {
    "date": "2026-01-23",
    "close": 22659.0,
    "open": 22843.0,
    "high": 23112.0,
    "low": 22206.0,
    "volume": 1440141000
  },
  {
    "date": "2026-01-24",
    "close": 22373.0,
    "open": 22344.0,
    "high": 22821.0,
    "low": 21926.0,
    "volume": 159120000
  },
  {
    "date": "2026-01-25",
    "close": 22448.0,
    "open": 22361.0,
    "high": 22897.0,
    "low": 22000.0,
    "volume": 787307000
  },
  {
    "date": "2026-01-26",
    "close": 22396.0,
    "open": 22444.0,
    "high": 22844.0,
    "low": 21948.0,
    "volume": 4200134000
  },
  {
    "date": "2026-01-27",
    "close": 22569.0,
    "open": 22588.0,
    "high": 23021.0,
    "low": 22118.0,
    "volume": 3767878000
  },
  {
    "date": "2026-01-28",
    "close": 22990.0,
    "open": 23131.0,
    "high": 23450.0,
    "low": 22530.0,
    "volume": 3661886000
  },
  {
    "date": "2026-01-29",
    "close": 22638.0,
    "open": 22784.0,
    "high": 23090.0,
    "low": 22185.0,
    "volume": 2087419000
  },
  {
    "date": "2026-01-30",
    "close": 22267.0,
    "open": 22084.0,
    "high": 22713.0,
    "low": 21822.0,
    "volume": 1682280000
  }
]