[
  {
    "date": "2025-11-02",
    "close": 84860.0,
    "open": 85505.0,
    "high": 86557.0,
    "low": 83163.0,
    "volume": 298187000
  },
  {
    "date": "2025-11-03",
    "close": 83789.0,
    "open": 83289.0,
    "high": 85465.0,
    "low": 82114.0,
    "volume": 3536224000
  },
  {
    "date": "2025-11-04",
    "close": 84376.0,
    "open": 83667.0,
    "high": 86063.0,
    "low": 82688.0,
    "volume": 3062114000
  },
  {
    "date": "2025-11-05",
    "close": 85753.0,
    "open": 85712.0,
    "high": 87468.0,
    "low": 84038.0,
    "volume": 537371000
  },
  {
    "date": "2025-11-06",
    "close": 84001.0,
    "open": 83220.0,
    "high": 85681.0,
    "low": 82321.0,
    "volume": 1176196000
  },
  {
    "date": "2025-11-07",
    "close": 84571.0,
    "open": 84981.0,
    "high": 86262.0,
    "low": 82879.0,
    "volume": 2289454000
  },
  {
    "date": "2025-11-08",
    "close": 83828.0,
    "open": 84136.0,
    "high": 85505.0,
    "low": 82152.0,
    "volume": 711733000
  },
  {
    "date": "2025-11-09",
    "close": 83023.0,
    "open": 82937.0,
    "high": 84683.0,
    "low": 81362.0,
    "volume": 2285912000
  },
  {
    "date": "2025-11-10",
    "close": 83289.0,
    "open": 83913.0,
    "high": 84955.0,
    "low": 81623.0,
    "volume": 2314744000
  },
  {
    "date": "2025-11-11",
    "close": 85360.0,
    "open": 84813.0,
    "high": 87067.0,
    "low": 83653.0,
    "volume": 1110702000
  },
  {
    "date": "2025-11-12",
    "close": 85732.0,
    "open": 86266.0,
    "high": 87446.0,
    "low": 84017.0,
    "volume": 912924000
  },
  {
    "date": "2025-11-13",
    "close": 84555.0,
    "open": 83990.0,
    "high": 86246.0,
    "low": 82864.0,
    "volume": 3251711000
  },
  {
    "date": "2025-11-14",
    "close": 84214.0,
    "open": 83725.0,
    "high": 85899.0,
    "low": 82530.0,
    "volume": 2193407000
  },
  {
    "date": "2025-11-15",
    "close": 84988.0,
    "open": 85507.0,
    "high": 86688.0,
    "low": 83288.0,
    "volume": 3495368000
  },
  {
    "date": "2025-11-16",
    "close": 82918.0,
    "open": 83442.0,
    "high": 84577.0,
    "low": 81260.0,
    "volume": 3294163000
  },
  {
    "date": "2025-11-17",
    "close": 83100.0,
    "open": 82878.0,
    "high": 84762.0,
    "low": 81438.0,
    "volume": 1839095000
  },
  {
    "date": "2025-11-18",
    "close": 85855.0,
    "open": 86353.0,
    "high": 87573.0,
    "low": 84138.0,
    "volume": 4919319000
  },
  {
    "date": "2025-11-19",
    "close": 85649.0,
    "open": 85829.0,
    "high": 87362.0,
    "low": 83936.0,
    "volume": 4898657000
  },
  {
    "date": "2025-11-20",
    "close": 83630.0,
    "open": 83269.0,
    "high": 85303.0,
    "low": 81957.0,
    "volume": 149622000
  },
  {
    "date": "2025-11-21",
    "close": 84498.0,
    "open": 83971.0,
    "high": 86188.0,
    "low": 82808.0,
    "volume": 703684000
  },
  {
    "date": "2025-11-22",
    "close": 83972.0,
    "open": 83286.0,
    "high": 85652.0,
    "low": 82293.0,
    "volume": 3215530000
  },
  {
    "date": "2025-11-23",
    "close": 85898.0,
    "open": 85041.0,
    "high": 87616.0,
    "low": 84180.0,
    "volume": 3943542000
  },
  {
    "date": "2025-11-24",
    "close": 84411.0,
    "open": 84970.0,
    "high": 86099.0,
    "low": 82723.0,
    "volume": 2551597000
  },
  {
    "date": "2025-11-25",
    "close": 84338.0,
    "open": 83777.0,
    "high": 86025.0,
    "low": 82652.0,
    "volume": 1505992000
  },
  {
    "date": "2025-11-26",
    "close": 83528.0,
    "open": 82831.0,
    "high": 85198.0,
    "low": 81857.0,
    "volume": 3495052000
  },
  {
    "date": "2025-11-27",
    "close": 84792.0,
    "open": 84176.0,
    "high": 86488.0,
    "low": 83096.0,
    "volume": 1312696000
  },
  {
    "date": "2025-11-28",
    "close": 83124.0,
    "open": 82308.0,
    "high": 84787.0,
    "low": 81462.0,
    "volume": 907971000
  },
  {
    "date": "2025-11-29",
    "close": 85526.0,
    "open": 85032.0,
    "high": 87236.0,
    "low": 83815.0,
    "volume": 3191481000
  },
  {
    "date": "2025-11-30",
    "close": 85537.0,
    "open": 85831.0,
    "high": 87248.0,
    "low": 83827.0,
    "volume": 1592580000
  },
  {
    "date": "2025-12-01",
    "close": 85480.0,
    "open": 84671.0,
    "high": 87190.0,
    "low": 83771.0,
    "volume": 4990712000
  },
  {
    "date": "2025-12-02",
    "close": 85200.0,
    "open": 85989.0,
    "high": 86904.0,
    "low": 83496.0,
    "volume": 2671142000
  },
  {
    "date": "2025-12-03",
    "close": 84793.0,
    "open": 84684.0,
    "high": 86489.0,
    "low": 83097.0,
    "volume": 3968030000
  },
  {
    "date": "2025-12-04",
    "close": 85793.0,
    "open": 85552.0,
    "high": 87509.0,
    "low": 84078.0,
    "volume": 2932055000
  },
  {
    "date": "2025-12-05",
    "close": 83984.0,
    "open": 84441.0,
    "high": 85663.0,
    "low": 82304.0,
    "volume": 4413572000
  },
  {
    "date": "2025-12-06",
    "close": 84048.0,
    "open": 84882.0,
    "high": 85729.0,
    "low": 82367.0,
    "volume": 1593588000
  },
  {
    "date": "2025-12-07",
    "close": 83201.0,
    "open": 83498.0,
    "high": 84865.0,
    "low": 81537.0,
    "volume": 1296308000
  },
  {
    "date": "2025-12-08",
    "close": 84404.0,
    "open": 83997.0,
    "high": 86092.0,
    "low": 82716.0,
    "volume": 3042440000
  },
  {
    "date": "2025-12-09",
    "close": 84146.0,
    "open": 84190.0,
    "high": 85829.0,
    "low": 82463.0,
    "volume": 4769200000
  },
  {
    "date": "2025-12-10",
    "close": 83157.0,
    "open": 83296.0,
    "high": 84820.0,
    "low": 81494.0,
    "volume": 1127001000
  },
  {
    "date": "2025-12-11",
    "close": 83194.0,
    "open": 82572.0,
    "high": 84858.0,
    "low": 81531.0,
    "volume": 1715313000
  },
  {
    "date": "2025-12-12",
    "close": 85938.0,
    "open": 85475.0,
    "high": 87657.0,
    "low": 84219.0,
    "volume": 887230000
  },
  {
    "date": "2025-12-13",
    "close": 82849.0,
    "open": 82724.0,
    "high": 84506.0,
    "low": 81192.0,
    "volume": 1149341000
  },
  {
    "date": "2025-12-14",
    "close": 83028.0,
    "open": 83021.0,
    "high": 84688.0,
    "low": 81367.0,
    "volume": 2345843000
  },
  {
    "date": "2025-12-15",
    "close": 83070.0,
    "open": 82541.0,
    "high": 84731.0,
    "low": 81409.0,
    "volume": 3114987000
  },
  {
    "date": "2025-12-16",
    "close": 83221.0,
    "open": 83521.0,
    "high": 84885.0,
    "low": 81557.0,
    "volume": 3200861000
  },
  {
    "date": "2025-12-17",
    "close": 83149.0,
    "open": 83811.0,
    "high": 84812.0,
    "low": 81486.0,
    "volume": 470257000
  },
  {
    "date": "2025-12-18",
    "close": 83134.0,
    "open": 83892.0,
    "high": 84797.0,
    "low": 81472.0,
    "volume": 1977255000
  },
  {
    "date": "2025-12-19",
    "close": 83849.0,
    "open": 83371.0,
    "high": 85526.0,
    "low": 82172.0,
    "volume": 2135499000
  },
  {
    "date": "2025-12-20",
    "close": 84159.0,
    "open": 84990.0,
    "high": 85842.0,
    "low": 82475.0,
    "volume": 3611080000
  },
  {
    "date": "2025-12-21",
    "close": 85409.0,
    "open": 85208.0,
    "high": 87117.0,
    "low": 83701.0,
    "volume": 2655141000
  },
  {
    "date": "2025-12-22",
    "close": 84292.0,
    "open": 84481.0,
    "high": 85978.0,
    "low": 82607.0,
    "volume": 1942329000
  },
  {
    "date": "2025-12-23",
    "close": 82810.0,
    "open": 82643.0,
    "high": 84466.0,
    "low": 81153.0,
    "volume": 833388000
  },
  {
    "date": "2025-12-24",
    "close": 83049.0,
    "open": 83223.0,
    "high": 84710.0,
    "low": 81388.0,
    "volume": 4631907000
  },
  {
    "date": "2025-12-25",
    "close": 83671.0,
    "open": 83689.0,
    "high": 85344.0,
    "low": 81998.0,
    "volume": 4508840000
  },
  {
    "date": "2025-12-26",
    "close": 84519.0,
    "open": 84955.0,
    "high": 86209.0,
    "low": 82829.0,
    "volume": 3562991000
  },
  {
    "date": "2025-12-27",
    "close": 85725.0,
    "open": 86255.0,
    "high": 87440.0,
    "low": 84011.0,
    "volume": 2293507000
  },
  {
    "date": "2025-12-28",
    "close": 84938.0,
    "open": 85730.0,
    "high": 86637.0,
    "low": 83240.0,
    "volume": 2108217000
  },
  {
    "date": "2025-12-29",
    "close": 85075.0,
    "open": 85756.0,
    "high": 86776.0,
    "low": 83373.0,
    "volume": 375145000
  },
  {
    "date": "2025-12-30",
    "close": 85311.0,
    "open": 85388.0,
    "high": 87017.0,
    "low": 83605.0,
    "volume": 3850660000
  },
  {
    "date": "2025-12-31",
    "close": 84238.0,
    "open": 84558.0,
    "high": 85922.0,
    "low": 82553.0,
    "volume": 4545521000
  },
  {
    "date": "2026-01-01",
    "close": 82882.0,
    "open": 83668.0,
    "high": 84539.0,
    "low": 81224.0,
    "volume": 2131664000
  },
  {
    "date": "2026-01-02",
    "close": 83101.0,
    "open": 83236.0,
    "high": 84763.0,
    "low": 81439.0,
    "volume": 4297581000
  },
  {
    "date": "2026-01-03",
    "close": 83610.0,
    "open": 82892.0,
    "high": 85282.0,
    "low": 81937.0,
    "volume": 1512932000
  },
  {
    "date": "2026-01-04",
    "close": 83823.0,
    "open": 84312.0,
    "high": 85500.0,
    "low": 82147.0,
    "volume": 4466441000
  },
  {
    "date": "2026-01-05",
    "close": 83416.0,
    "open": 83700.0,
    "high": 85084.0,
    "low": 81747.0,
    "volume": 3977145000
  },
  {
    "date": "2026-01-06",
    "close": 83809.0,
    "open": 83187.0,
    "high": 85485.0,
    "low": 82133.0,
    "volume": 4826839000
  },
  {
    "date": "2026-01-07",
    "close": 83365.0,
    "open": 82638.0,
    "high": 85032.0,
    "low": 81698.0,
    "volume": 3174634000
  },
  {
    "date": "2026-01-08",
    "close": 83404.0,
    "open": 82748.0,
    "high": 85072.0,
    "low": 81736.0,
    "volume": 1036913000
  },
  {
    "date": "2026-01-09",
    "close": 83266.0,
    "open": 83130.0,
    "high": 84931.0,
    "low": 81601.0,
    "volume": 3210621000
  },
  {
    "date": "2026-01-10",
    "close": 84275.0,
    "open": 84643.0,
    "high": 85961.0,
    "low": 82590.0,
    "volume": 2513835000
  },
  {
    "date": "2026-01-11",
    "close": 83447.0,
    "open": 83779.0,
    "high": 85116.0,
    "low": 81778.0,
    "volume": 4968045000
  },
  {
    "date": "2026-01-12",
    "close": 86021.0,
    "open": 86681.0,
    "high": 87741.0,
    "low": 84300.0,
    "volume": 3757182000
  },
  {
    "date": "2026-01-13",
    "close": 84367.0,
    "open": 84312.0,
    "high": 86054.0,
    "low": 82679.0,
    "volume": 4955717000
  },
  {
    "date": "2026-01-14",
    "close": 84678.0,
    "open": 84843.0,
    "high": 86372.0,
    "low": 82984.0,
    "volume": 1865043000
  },
  {
    "date": "2026-01-15",
    "close": 83002.0,
    "open": 82512.0,
    "high": 84662.0,
    "low": 81342.0,
    "volume": 3952465000
  },
  {
    "date": "2026-01-16",
    "close": 84462.0,
    "open": 85212.0,
    "high": 86151.0,
    "low": 82773.0,
    "volume": 3836042000
  },
  {
    "date": "2026-01-17",
    "close": 84482.0,
    "open": 84892.0,
    "high": 86172.0,
    "low": 82793.0,
    "volume": 882877000
  },
  {
    "date": "2026-01-18",
    "close": 85544.0,
    "open": 84816.0,
    "high": 87255.0,
    "low": 83833.0,
    "volume": 3759590000
  },
  {
    "date": "2026-01-19",
    "close": 83533.0,
    "open": 84252.0,
    "high": 85204.0,
    "low": 81863.0,
    "volume": 3187820000
  },
  {
    "date": "2026-01-20",
    "close": 83125.0,
    "open": 83824.0,
    "high": 84787.0,
    "low": 81462.0,
    "volume": 950556000
  },
  {
    "date": "2026-01-21",
    "close": 85637.0,
    "open": 85337.0,
    "high": 87349.0,
    "low": 83924.0,
    "volume": 3712292000
  },
  {
    "date": "2026-01-22",
    "close": 84669.0,
    "open": 84713.0,
    "high": 86363.0,
    "low": 82976.0,
    "volume": 1152658000
  },
  {
    "date": "2026-01-23",
    "close": 85216.0,
    "open": 85753.0,
    "high": 86920.0,
    "low": 83512.0,
    "volume": 2414100000
  },
  {
    "date": "2026-01-24",
    "close": 83053.0,
    "open": 83636.0,
    "high": 84714.0,
    "low": 81392.0,
    "volume": 635260000
  },
  {
    "date": "2026-01-25",
    "close": 85903.0,
    "open": 85069.0,
    "high": 87621.0,
    "low": 84185.0,
    "volume": 269670000
  },
  {
    "date": "2026-01-26",
    "close": 83143.0,
    "open": 83139.0,
    "high": 84806.0,
    "low": 81480.0,
    "volume": 3943789000
  },
  {
    "date": "2026-01-27",
    "close": 83698.0,
    "open": 84438.0,
    "high": 85371.0,
    "low": 82024.0,
    "volume": 589309000
  },
  {
    "date": "2026-01-28",
    "close": 83026.0,
    "open": 83562.0,
    "high": 84687.0,
    "low": 81366.0,
    "volume": 4283202000
  },
  {
    "date": "2026-01-29",
    "close": 82820.0,
    "open": 82731.0,
    "high": 84476.0,
    "low": 81163.0,
    "volume": 4125204000
  },
  {
    "date": "2026-01-30",
    "close": 84139.0,
    "open": 83303.0,
    "high": 85822.0,
    "low": 82456.0,
    "volume": 4995149000
  }
]