[
  {
    "date": "2025-10-28",
    "close": 17300.0,
    "open": 17200.0,
    "high": 17350.0,
    "low": 16950.0,
    "volume": 1500800
  },
  {
    "date": "2025-10-29",
    "close": 17650.0,
    "open": 17300.0,
    "high": 17750.0,
    "low": 17300.0,
    "volume": 2699000
  },
  {
    "date": "2025-10-30",
    "close": 17450.0,
    "open": 17750.0,
    "high": 17750.0,
    "low": 17400.0,
    "volume": 1120300
  },
  {
    "date": "2025-10-31",
    "close": 17600.0,
    "open": 17550.0,
    "high": 18050.0,
    "low": 17550.0,
    "volume": 3386000
  },
  {
    "date": "2025-11-03",
    "close": 17400.0,
    "open": 17850.0,
    "high": 17900.0,
    "low": 17400.0,
    "volume": 1556600
  },
  {
    "date": "2025-11-04",
    "close": 17300.0,
    "open": 17450.0,
    "high": 17500.0,
    "low": 16850.0,
    "volume": 2576400
  },
  {
    "date": "2025-11-05",
    "close": 18000.0,
    "open": 17250.0,
    "high": 18150.0,
    "low": 17150.0,
    "volume": 6399000
  },
  {
    "date": "2025-11-06",
    "close": 17900.0,
    "open": 18100.0,
    "high": 18100.0,
    "low": 17600.0,
    "volume": 1583200
  },
  {
    "date": "2025-11-07",
    "close": 17600.0,
    "open": 17900.0,
    "high": 18200.0,
    "low": 17600.0,
    "volume": 4162800
  },
  {
    "date": "2025-11-10",
    "close": 17400.0,
    "open": 17700.0,
    "high": 17700.0,
    "low": 17300.0,
    "volume": 1496000
  },
  {
    "date": "2025-11-11",
    "close": 17250.0,
    "open": 17400.0,
    "high": 17500.0,
    "low": 17200.0,
    "volume": 1747900
  },
  {
    "date": "2025-11-12",
    "close": 17600.0,
    "open": 17350.0,
    "high": 17800.0,
    "low": 17350.0,
    "volume": 1741200
  },
  {
    "date": "2025-11-13",
    "close": 18500.0,
    "open": 17600.0,
    "high": 18500.0,
    "low": 17550.0,
    "volume": 8369300
  },
  {
    "date": "2025-11-14",
    "close": 18500.0,
    "open": 18500.0,
    "high": 18700.0,
    "low": 18350.0,
    "volume": 2954500
  },
  {
    "date": "2025-11-17",
    "close": 18700.0,
    "open": 18700.0,
    "high": 18700.0,
    "low": 18300.0,
    "volume": 3730600
  },
  {
    "date": "2025-11-18",
    "close": 18550.0,
    "open": 18750.0,
    "high": 18800.0,
    "low": 18400.0,
    "volume": 3284600
  },
  {
    "date": "2025-11-19",
    "close": 18350.0,
    "open": 18550.0,
    "high": 18650.0,
    "low": 18300.0,
    "volume": 3812400
  },
  {
    "date": "2025-11-20",
    "close": 18300.0,
    "open": 18500.0,
    "high": 18600.0,
    "low": 18100.0,
    "volume": 2862900
  },
  {
    "date": "2025-11-21",
    "close": 18000.0,
    "open": 18250.0,
    "high": 18300.0,
    "low": 17900.0,
    "volume": 2679900
  },
  {
    "date": "2025-11-24",
    "close": 17850.0,
    "open": 18100.0,
    "high": 18200.0,
    "low": 17850.0,
    "volume": 1546800
  },
  {
    "date": "2025-11-25",
    "close": 18500.0,
    "open": 18150.0,
    "high": 18850.0,
    "low": 18100.0,
    "volume": 8695600
  },
  {
    "date": "2025-11-26",
    "close": 19050.0,
    "open": 18700.0,
    "high": 19150.0,
    "low": 18650.0,
    "volume": 5238500
  },
  {
    "date": "2025-11-27",
    "close": 18600.0,
    "open": 19100.0,
    "high": 19150.0,
    "low": 18600.0,
    "volume": 3277500
  },
  {
    "date": "2025-11-28",
    "close": 18850.0,
    "open": 18750.0,
    "high": 19400.0,
    "low": 18750.0,
    "volume": 8734000
  },
  {
    "date": "2025-12-01",
    "close": 18750.0,
    "open": 19100.0,
    "high": 19250.0,
    "low": 18750.0,
    "volume": 2412900
  },
  {
    "date": "2025-12-02",
    "close": 19200.0,
    "open": 18850.0,
    "high": 19400.0,
    "low": 18800.0,
    "volume": 5564800
  },
  {
    "date": "2025-12-03",
    "close": 18750.0,
    "open": 19250.0,
    "high": 19250.0,
    "low": 18750.0,
    "volume": 4252400
  },
  {
    "date": "2025-12-04",
    "close": 19000.0,
    "open": 18950.0,
    "high": 19300.0,
    "low": 18800.0,
    "volume": 6575600
  },
  {
    "date": "2025-12-05",
    "close": 18900.0,
    "open": 19000.0,
    "high": 19350.0,
    "low": 18900.0,
    "volume": 3925200
  },
  {
    "date": "2025-12-08",
    "close": 18400.0,
    "open": 18950.0,
    "high": 19000.0,
    "low": 18350.0,
    "volume": 4693900
  },
  {
    "date": "2025-12-09",
    "close": 18100.0,
    "open": 18400.0,
    "high": 18500.0,
    "low": 17950.0,
    "volume": 4302900
  },
  {
    "date": "2025-12-10",
    "close": 18050.0,
    "open": 18150.0,
    "high": 18300.0,
    "low": 18050.0,
    "volume": 1701800
  },
  {
    "date": "2025-12-11",
    "close": 18000.0,
    "open": 18200.0,
    "high": 18300.0,
    "low": 17950.0,
    "volume": 1469900
  },
  {
    "date": "2025-12-12",
    "close": 17400.0,
    "open": 18000.0,
    "high": 18100.0,
    "low": 17400.0,
    "volume": 3843700
  },
  {
    "date": "2025-12-15",
    "close": 17850.0,
    "open": 17400.0,
    "high": 17950.0,
    "low": 17300.0,
    "volume": 3439400
  },
  {
    "date": "2025-12-16",
    "close": 18350.0,
    "open": 17800.0,
    "high": 18350.0,
    "low": 17600.0,
    "volume": 2304900
  },
  {
    "date": "2025-12-17",
    "close": 18350.0,
    "open": 18250.0,
    "high": 18600.0,
    "low": 18100.0,
    "volume": 2134500
  },
  {
    "date": "2025-12-18",
    "close": 18300.0,
    "open": 18350.0,
    "high": 18500.0,
    "low": 18250.0,
    "volume": 1271600
  },
  {
    "date": "2025-12-19",
    "close": 18250.0,
    "open": 18300.0,
    "high": 18550.0,
    "low": 18250.0,
    "volume": 1560700
  },
  {
    "date": "2025-12-22",
    "close": 18500.0,
    "open": 18250.0,
    "high": 18500.0,
    "low": 18250.0,
    "volume": 1352700
  },
  {
    "date": "2025-12-23",
    "close": 18450.0,
    "open": 18600.0,
    "high": 18850.0,
    "low": 18450.0,
    "volume": 3524200
  },
  {
    "date": "2025-12-24",
    "close": 18900.0,
    "open": 18500.0,
    "high": 18900.0,
    "low": 18500.0,
    "volume": 4089100
  },
  {
    "date": "2025-12-25",
    "close": 18400.0,
    "open": 18900.0,
    "high": 18950.0,
    "low": 18400.0,
    "volume": 1783000
  },
  {
    "date": "2025-12-26",
    "close": 18500.0,
    "open": 18350.0,
    "high": 18700.0,
    "low": 18200.0,
    "volume": 2005600
  },
  {
    "date": "2025-12-29",
    "close": 18950.0,
    "open": 18600.0,
    "high": 19200.0,
    "low": 18600.0,
    "volume": 3911600
  },
  {
    "date": "2025-12-30",
    "close": 18800.0,
    "open": 19100.0,
    "high": 19100.0,
    "low": 18650.0,
    "volume": 1876300
  },
  {
    "date": "2025-12-31",
    "close": 18400.0,
    "open": 18850.0,
    "high": 18850.0,
    "low": 18400.0,
    "volume": 1956100
  },
  {
    "date": "2026-01-05",
    "close": 18800.0,
    "open": 18600.0,
    "high": 19100.0,
    "low": 18400.0,
    "volume": 3823400
  },
  {
    "date": "2026-01-06",
    "close": 19200.0,
    "open": 18850.0,
    "high": 19400.0,
    "low": 18800.0,
    "volume": 7416900
  },
  {
    "date": "2026-01-07",
    "close": 20500.0,
    "open": 19300.0,
    "high": 20500.0,
    "low": 19250.0,
    "volume": 12372000
  },
  {
    "date": "2026-01-08",
    "close": 20750.0,
    "open": 21000.0,
    "high": 21500.0,
    "low": 20500.0,
    "volume": 13036900
  },
  {
    "date": "2026-01-09",
    "close": 20300.0,
    "open": 20650.0,
    "high": 21350.0,
    "low": 20200.0,
    "volume": 6804500
  },
  {
    "date": "2026-01-12",
    "close": 19700.0,
    "open": 20750.0,
    "high": 20750.0,
    "low": 19500.0,
    "volume": 8863000
  },
  {
    "date": "2026-01-13",
    "close": 21050.0,
    "open": 19850.0,
    "high": 21050.0,
    "low": 19700.0,
    "volume": 6912700
  },
  {
    "date": "2026-01-14",
    "close": 20900.0,
    "open": 21550.0,
    "high": 22100.0,
    "low": 20700.0,
    "volume": 12244100
  },
  {
    "date": "2026-01-15",
    "close": 20500.0,
    "open": 20900.0,
    "high": 21100.0,
    "low": 20300.0,
    "volume": 5422200
  },
  {
    "date": "2026-01-16",
    "close": 20600.0,
    "open": 20650.0,
    "high": 21300.0,
    "low": 20450.0,
    "volume": 5430000
  },
  {
    "date": "2026-01-19",
    "close": 20600.0,
    "open": 20900.0,
    "high": 21050.0,
    "low": 20400.0,
    "volume": 3024600
  },
  {
    "date": "2026-01-20",
    "close": 20300.0,
    "open": 20600.0,
    "high": 20850.0,
    "low": 20300.0,
    "volume": 4598700
  },
  {
    "date": "2026-01-21",
    "close": 20500.0,
    "open": 20100.0,
    "high": 20500.0,
    "low": 19350.0,
    "volume": 7474700
  },
  {
    "date": "2026-01-22",
    "close": 20850.0,
    "open": 20850.0,
    "high": 21150.0,
    "low": 20500.0,
    "volume": 7182700
  },
  {
    "date": "2026-01-23",
    "close": 19850.0,
    "open": 21000.0,
    "high": 21000.0,
    "low": 19650.0,
    "volume": 4295900
  },
  {
    "date": "2026-01-26",
    "close": 20400.0,
    "open": 19900.0,
    "high": 20850.0,
    "low": 19850.0,
    "volume": 6395900
  },
  {
    "date": "2026-01-27",
    "close": 20550.0,
    "open": 20400.0,
    "high": 21000.0,
    "low": 19900.0,
    "volume": 3686100
  },
  {
    "date": "2026-01-28",
    "close": 21000.0,
    "open": 20850.0,
    "high": 21450.0,
    "low": 20500.0,
    "volume": 8278300
  },
  {
    "date": "2026-01-29",
    "close": 20500.0,
    "open": 21100.0,
    "high": 21100.0,
    "low": 20500.0,
    "volume": 2513200
  },
  {
    "date": "2026-01-30",
    "close": 20750.0,
    "open": 20800.0,
    "high": 21400.0,
    "low": 20700.0,
    "volume": 4639700
  }
]